bfsplate2d/__init__.py
bfsplate2d/bfsplate2d.cp36-win_amd64.pyd
bfsplate2d/quadrature.py
bfsplate2d/version.py
bfsplate2d-0.3.0.data/data/LICENSE
bfsplate2d-0.3.0.data/data/README.md
bfsplate2d-0.3.0.dist-info/LICENSE
bfsplate2d-0.3.0.dist-info/METADATA
bfsplate2d-0.3.0.dist-info/WHEEL
bfsplate2d-0.3.0.dist-info/top_level.txt
bfsplate2d-0.3.0.dist-info/RECORD
