Metadata-Version: 1.1
Name: bfsplate2d
Version: 0.3.0
Summary: Implementation of the BFS plate finite element in 2D
Home-page: https://github.com/saullocastro/bfsplate2d
Author: Saullo G. P. Castro
Author-email: S.G.P.Castro@tudelft.nl
License: 2-Clause BSD
Keywords: finite elements shell plate structural analysis buckling vibration dynamics
Platform: UNKNOWN
Classifier: Development Status :: 4 - Beta
Classifier: Intended Audience :: Education
Classifier: Intended Audience :: Science/Research
Classifier: Intended Audience :: Developers
Classifier: Topic :: Scientific/Engineering :: Mathematics
Classifier: Topic :: Education
Classifier: License :: OSI Approved :: BSD License
Classifier: Programming Language :: Python :: 3.6
Classifier: Programming Language :: Python :: 3.7
Classifier: Programming Language :: Python :: 3.8
Classifier: Operating System :: Microsoft :: Windows
Classifier: Operating System :: Unix
